{
  "summary_type": "user_daily",
  "generation_time": "2026-02-04T01:37:40.756871",
  "tweet_count": 58,
  "summary": "## 核心动态\n- SpaceX 收购 xAI，并公开强调两家公司合并为“一家公司”，目标是把火箭、卫星、互联网和 AI 串联起来，推动“太空为 AI 提供算力”的长期战略。  \n- 公开信（被大量转发）提出把 AI 数据中心搬到轨道/月球、用星舰大规模发射卫星并最终迈向卡尔达肖夫 II 型文明的宏大愿景，说明这是合并后的明确路线图与技术/商业逻辑。  \n- 强力推广 Grok 及其生态（App 升级、Grok Imagine 文生/图转视 频、Batch API 与无版权“Grokipedia”定位），把 xAI 产品迅速推向用户和开发者级别的生产工具。  \n- 围绕 X/Starlink 的产品与政策动作：Starlink 推出 Direct-to-Cell 在欧洲扩展、One NZ 补充覆盖，同时对法国司法行动和西班牙政府的监管举措公开批评并称其为政治攻击。\n\n## 值得关注\n- 多条推文和转发反复把“K2 / 卡尔达肖夫 II 型文明”作为底色（“Anything less than K2 is feeble” 等），既是技术愿景也是对外传播的强烈品牌叙事。  \n- Grok 的落地动作非常具体：鼓励下载、推 Batch API、宣布新视频模型并提供模板/SDK，显示从宣传到产品化的快速推进。  \n- 在政经话题上，明显支持立法方向（大量转发支持 Voter ID / SAVE Act 的内容）并公开抨击欧洲多国政府与官员（对西班牙首相 Sánchez、法国稽查行动等语气强烈）。  \n- 商业/基础设施进展并行：特斯拉推出 Model Y AWD（价格与参数被多次转发），Boring Company 获得迪拜 Loop 合约，且有 xAI/马斯克向受灾地区捐赠发电机的消息被放大。  \n- 宣传节奏快且覆盖面广：从太空宏愿、AI 产品到政治立场和商业新闻，推文组合同时服务于投资者、用户与支持者的多重受众。",
  "metadata": {
    "original_tweets": 27,
    "retweets": 31,
    "media_tweets": 3,
    "data_hash": "276973ae",
    "user": "elonmusk"
  }
}