{
  "user": {
    "screen_name": "elonmusk",
    "name": "Elon Musk",
    "description": "",
    "followers_count": 232490187,
    "verified": false,
    "is_blue_verified": true
  },
  "date": "20260119",
  "last_updated": "2026-01-19T04:25:30.821421",
  "tweet_count": 4,
  "tweets": [
    {
      "id": "2013050946306052180",
      "text": "RT @jeffreyweichsel: Just saw this snake in Palo Alto.  @Grok what kind of snake is this and is it dangerous? https://t.co/3OaWh6YMUH",
      "created_at": "Mon Jan 19 00:48:40 +0000 2026",
      "lang": "en",
      "media": [
        {
          "type": "photo",
          "id": "2013038110594998272",
          "url": "https://pbs.twimg.com/media/G--_fv1WoAAg1BJ.jpg"
        }
      ],
      "retweet": {
        "id": "2013038117901799572",
        "text": "Just saw this snake in Palo Alto.  @Grok what kind of snake is this and is it dangerous? https://t.co/3OaWh6YMUH",
        "created_at": "Sun Jan 18 23:57:42 +0000 2026",
        "lang": "en",
        "media": [
          {
            "type": "photo",
            "id": "2013038110594998272",
            "url": "https://pbs.twimg.com/media/G--_fv1WoAAg1BJ.jpg"
          }
        ],
        "retweet": null,
        "quoted": null,
        "user": {
          "id": "818165325946638336",
          "name": "Jeffrey Weichsel",
          "screen_name": "jeffreyweichsel",
          "description": "",
          "followers_count": 8999,
          "friends_count": 707,
          "verified": false,
          "is_blue_verified": true
        },
        "stats": {
          "retweet_count": 233,
          "favorite_count": 1563,
          "reply_count": 666,
          "quote_count": 34
        }
      },
      "quoted": null,
      "stats": {
        "retweet_count": 233,
        "favorite_count": 0,
        "reply_count": 0,
        "quote_count": 0
      }
    },
    {
      "id": "2013068183557849104",
      "text": "RT @GuntherEagleman: 🚨 BREAKING: Speaker Johnson &amp; Steve Scalise are DROPPING the HAMMER! \n\nThey’re about to pass a TURBOCHARGED SAVE Act:…",
      "created_at": "Mon Jan 19 01:57:10 +0000 2026",
      "lang": "en",
      "media": [],
      "retweet": {
        "id": "2013046379778642296",
        "text": "🚨 BREAKING: Speaker Johnson & Steve Scalise are DROPPING the HAMMER! \n\nThey’re about to pass a TURBOCHARGED SAVE Act:\n\n•  Requires PHOTO ID\n\n•  Proves CITIZENSHIP to vote\n“The SAVE Act plus—a picture ID requirement.”\n\n“There are states PREVENTING voter ID, a recipe for fraud!”\n\nThis lights a FIRE under the Senate RINOs. Bring it to the floor FULL-STEAM AHEAD!\n\nNo more stolen elections. GET IT PASSED!",
        "created_at": "Mon Jan 19 00:30:32 +0000 2026",
        "lang": "en",
        "media": [
          {
            "type": "video",
            "id": "2013046322681581569",
            "url": "https://video.twimg.com/amplify_video/2013046322681581569/vid/avc1/1920x1080/WM6te0zrZ9U9LZxo.mp4?tag=21",
            "bitrate": 10368000
          }
        ],
        "retweet": null,
        "quoted": null,
        "user": {
          "id": "1355721251180961792",
          "name": "Gunther Eagleman™",
          "screen_name": "GuntherEagleman",
          "description": "David J. Freeman - Political Commentator - America First - MAGA - Christian",
          "followers_count": 1673546,
          "friends_count": 102842,
          "verified": false,
          "is_blue_verified": true
        },
        "stats": {
          "retweet_count": 4304,
          "favorite_count": 18431,
          "reply_count": 1187,
          "quote_count": 173
        }
      },
      "quoted": null,
      "stats": {
        "retweet_count": 4304,
        "favorite_count": 0,
        "reply_count": 0,
        "quote_count": 0
      }
    },
    {
      "id": "2013096610754920625",
      "text": "The idea grows more appealing every day 😂",
      "created_at": "Mon Jan 19 03:50:08 +0000 2026",
      "lang": "en",
      "media": [],
      "retweet": null,
      "quoted": {
        "id": "2013022817143369797",
        "text": "I’m running enough companies right now but fuck it… What’s one more?",
        "created_at": "Sun Jan 18 22:56:54 +0000 2026",
        "lang": "en",
        "media": [],
        "retweet": null,
        "quoted": null,
        "user": {
          "id": "1104564502220161026",
          "name": "Shawn Ryan",
          "screen_name": "ShawnRyan762",
          "description": "FMR Navy SEAL/CIA Contractor. Host of the @shawnryanshow",
          "followers_count": 1205689,
          "friends_count": 1092,
          "verified": false,
          "is_blue_verified": true
        },
        "stats": {
          "retweet_count": 139,
          "favorite_count": 3770,
          "reply_count": 217,
          "quote_count": 12
        }
      },
      "stats": {
        "retweet_count": 494,
        "favorite_count": 5731,
        "reply_count": 1048,
        "quote_count": 54
      }
    },
    {
      "id": "2013101288381456809",
      "text": "RT @MarioNawfal: 🇺🇸 NICK SHIRLEY CALLS OUT ANDREW CALLAGHAN: \"YOU TAMPERED WITH OUR INTERVIEW AND I’VE GOT THE RECEIPTS\"\n\nNick Shirley caug…",
      "created_at": "Mon Jan 19 04:08:43 +0000 2026",
      "lang": "en",
      "media": [],
      "retweet": {
        "id": "2013076446776844606",
        "text": "🇺🇸 NICK SHIRLEY CALLS OUT ANDREW CALLAGHAN: \"YOU TAMPERED WITH OUR INTERVIEW AND I’VE GOT THE RECEIPTS\"\n\nNick Shirley caught Channel 5’s Andrew Callaghan chopping their 2.5-hour convo on Minnesota daycare fraud down to a slick hour.\n\nCallaghan cut every part where he fumbled or got called out.\n\nNick dropped the unedited footage to prove it, showing how the final cut twisted the story.\n\nOne of the big edits? Dodging the stat that 86% of the fraud is tied to Somali networks.\n\nSource: YouTube, @nickshirleyy",
        "created_at": "Mon Jan 19 02:30:00 +0000 2026",
        "lang": "en",
        "media": [
          {
            "type": "video",
            "id": "2013072657554509824",
            "url": "https://video.twimg.com/amplify_video/2013072657554509824/vid/avc1/1080x1920/8vu3TNS4ZWlBsc4I.mp4?tag=21",
            "bitrate": 10368000
          }
        ],
        "retweet": null,
        "quoted": null,
        "user": {
          "id": "1319287761048723458",
          "name": "Mario Nawfal",
          "screen_name": "MarioNawfal",
          "description": "Largest Show on X | 24x7 News | Investor 700+ Startups | Founder @ibcgroupio , https://t.co/sw7OQ5KgAW",
          "followers_count": 2847057,
          "friends_count": 50182,
          "verified": false,
          "is_blue_verified": true
        },
        "stats": {
          "retweet_count": 1655,
          "favorite_count": 5806,
          "reply_count": 215,
          "quote_count": 30
        }
      },
      "quoted": null,
      "stats": {
        "retweet_count": 1655,
        "favorite_count": 0,
        "reply_count": 0,
        "quote_count": 0
      }
    }
  ]
}