{
  "user": {
    "screen_name": "elonmusk",
    "name": "Elon Musk",
    "description": "",
    "followers_count": 229122109,
    "verified": false,
    "is_blue_verified": true
  },
  "date": "20251119",
  "last_updated": "2025-11-19T16:06:18.093116",
  "tweet_count": 2,
  "tweets": [
    {
      "id": "1991034013205528693",
      "text": "Austin is booming!",
      "created_at": "Wed Nov 19 06:41:15 +0000 2025",
      "lang": "en",
      "media": [],
      "retweet": null,
      "quoted": {
        "id": "1990907950987145236",
        "text": "Look at the decline in population for young children (under age 5) in major cities from 2005 to 2024\nThis is catastrophic\n\nAustin +98%\nOrlando +89%\nRaleigh +87%\nCharlotte +81%\nDallas +81%\n\nChicago -31%\nBoston -33%\nNew York - 34%\nLA -36%\nSan Francisco -38% https://t.co/FxeWf16QUs",
        "created_at": "Tue Nov 18 22:20:19 +0000 2025",
        "lang": "en",
        "media": [
          {
            "type": "photo",
            "id": "1990906969264103424",
            "url": "https://pbs.twimg.com/media/G6EfVxvWIAAuWP-.jpg"
          }
        ],
        "retweet": null,
        "quoted": null,
        "user": {
          "id": "860337764776194049",
          "name": "Bobby Fijan",
          "screen_name": "bobbyfijan",
          "description": "Bill James of Floorplans | Building Rowhomes for Families \n\nPodcast: Why We Don't Build Apartments for Families ⬇️",
          "followers_count": 52476,
          "friends_count": 6458,
          "verified": false,
          "is_blue_verified": true
        },
        "stats": {
          "retweet_count": 182,
          "favorite_count": 1304,
          "reply_count": 178,
          "quote_count": 91
        }
      },
      "stats": {
        "retweet_count": 1205,
        "favorite_count": 8944,
        "reply_count": 1821,
        "quote_count": 89
      }
    },
    {
      "id": "1991166183014354973",
      "text": "https://t.co/ks152HcHV6, which will be renamed Encyclopedia Galactica when it is at least slightly deserving of the name, is a major project @xAI.\n\nThis is intended to be a massive open source repository of all knowledge about the Universe. \n\nMany copies will be distributed periodically throughout the solar system to preserve knowledge for future civilizations should ours perish or subside into barbarism. We take the lesson of the Library of Alexandria to heart.",
      "created_at": "Wed Nov 19 15:26:26 +0000 2025",
      "lang": "en",
      "media": [],
      "retweet": null,
      "quoted": {
        "id": "1990940533930311737",
        "text": "NEWS: xAI is hiring an engineer for Grokipedia.\n\nhttps://t.co/3ArMTPcjYh",
        "created_at": "Wed Nov 19 00:29:47 +0000 2025",
        "lang": "en",
        "media": [],
        "retweet": null,
        "quoted": null,
        "user": {
          "id": "752567226",
          "name": "X Daily News",
          "screen_name": "xDaily",
          "description": "Your #1 News source on everything 𝕏 + xAI | Contributors: @HXMnCK, @LohanSimpson @xUpdatesRadar and @swak_12 I | Hit Follow and sign up for notifications! 🔔",
          "followers_count": 328423,
          "friends_count": 5238,
          "verified": false,
          "is_blue_verified": true
        },
        "stats": {
          "retweet_count": 33,
          "favorite_count": 295,
          "reply_count": 29,
          "quote_count": 5
        }
      },
      "stats": {
        "retweet_count": 1561,
        "favorite_count": 12368,
        "reply_count": 2136,
        "quote_count": 178
      }
    }
  ]
}